bipol
