Metadata-Version: 1.1
Name: bipol
Version: 0.0.5
Summary: A bipol plugin
Home-page: https://github.com/patricksanders/bipol
Author: Patrick Sanders
Author-email: mail@patricksanders.net
License: MIT
Platform: UNKNOWN
Classifier: License :: OSI Approved :: MIT License
